simpleiso3166/__about__.py
simpleiso3166/__init__.py
simpleiso3166/aliases.py
simpleiso3166/base.py
simpleiso3166/errors.py
simpleiso3166/py.typed
simpleiso3166/generated/__init__.py
simpleiso3166/generated/data/__init__.py
simpleiso3166/generated/data/AD/__init__.py
simpleiso3166/generated/data/AE/__init__.py
simpleiso3166/generated/data/AF/__init__.py
simpleiso3166/generated/data/AG/__init__.py
simpleiso3166/generated/data/AI/__init__.py
simpleiso3166/generated/data/AL/__init__.py
simpleiso3166/generated/data/AM/__init__.py
simpleiso3166/generated/data/AO/__init__.py
simpleiso3166/generated/data/AQ/__init__.py
simpleiso3166/generated/data/AR/__init__.py
simpleiso3166/generated/data/AS/__init__.py
simpleiso3166/generated/data/AT/__init__.py
simpleiso3166/generated/data/AU/__init__.py
simpleiso3166/generated/data/AW/__init__.py
simpleiso3166/generated/data/AX/__init__.py
simpleiso3166/generated/data/AZ/__init__.py
simpleiso3166/generated/data/BA/__init__.py
simpleiso3166/generated/data/BB/__init__.py
simpleiso3166/generated/data/BD/__init__.py
simpleiso3166/generated/data/BE/__init__.py
simpleiso3166/generated/data/BF/__init__.py
simpleiso3166/generated/data/BG/__init__.py
simpleiso3166/generated/data/BH/__init__.py
simpleiso3166/generated/data/BI/__init__.py
simpleiso3166/generated/data/BJ/__init__.py
simpleiso3166/generated/data/BL/__init__.py
simpleiso3166/generated/data/BM/__init__.py
simpleiso3166/generated/data/BN/__init__.py
simpleiso3166/generated/data/BO/__init__.py
simpleiso3166/generated/data/BQ/__init__.py
simpleiso3166/generated/data/BR/__init__.py
simpleiso3166/generated/data/BS/__init__.py
simpleiso3166/generated/data/BT/__init__.py
simpleiso3166/generated/data/BV/__init__.py
simpleiso3166/generated/data/BW/__init__.py
simpleiso3166/generated/data/BY/__init__.py
simpleiso3166/generated/data/BZ/__init__.py
simpleiso3166/generated/data/CA/__init__.py
simpleiso3166/generated/data/CC/__init__.py
simpleiso3166/generated/data/CD/__init__.py
simpleiso3166-0.3.0.dist-info/METADATA
simpleiso3166-0.3.0.dist-info/WHEEL
simpleiso3166-0.3.0.dist-info/licenses/LICENSE
simpleiso3166-0.3.0.dist-info/RECORD
