Metadata-Version: 2.4
Name: simpleiso3166
Version: 0.3.0
Summary: Simple, strongly typed access to ISO 3166-1 and 3116-2
Project-URL: Changelog, https://github.com/stumpylog/simpleiso3166/blob/main/CHANGELOG.md
Project-URL: Documentation, https://github.com/stumpylog/simpleiso3166#readme
Project-URL: Issues, https://github.com/stumpylog/simpleiso3166/issues
Project-URL: Source, https://github.com/stumpylog/simpleiso3166
Author-email: Trenton H <rda0128ou@mozmail.com>
License-Expression: MPL-2.0
License-File: LICENSE
Keywords: 3166,country,iso,subdivision
Classifier: Development Status :: 4 - Beta
Classifier: Intended Audience :: Developers
Classifier: License :: OSI Approved :: Mozilla Public License 2.0 (MPL 2.0)
Classifier: Operating System :: OS Independent
Classifier: Programming Language :: Python
Classifier: Programming Language :: Python :: 3 :: Only
Classifier: Programming Language :: Python :: 3.9
Classifier: Programming Language :: Python :: 3.10
Classifier: Programming Language :: Python :: 3.11
Classifier: Programming Language :: Python :: 3.12
Classifier: Programming Language :: Python :: 3.13
Classifier: Programming Language :: Python :: 3.14
Classifier: Programming Language :: Python :: Implementation :: CPython
Classifier: Programming Language :: Python :: Implementation :: PyPy
Requires-Python: >=3.9
Provides-Extra: search
Requires-Dist: rapidfuzz; extra == 'search'
